{
	"elapsedTime": 836,
	"results": [
		{
			"barcodeFormat": "EAN13",
			"barcodeText": "0442222879956",
			"x1": 36,
			"y1": 690,
			"x2": 48,
			"y2": 356,
			"x3": 527,
			"y3": 373,
			"x4": 514,
			"y4": 708
		},
		{
			"barcodeFormat": "EAN13",
			"barcodeText": "0011110855893",
			"x1": 57,
			"y1": 685,
			"x2": 69,
			"y2": 362,
			"x3": 507,
			"y3": 378,
			"x4": 495,
			"y4": 701
		},
		{
			"barcodeFormat": "EAN13",
			"barcodeText": "0011110855893",
			"x1": 95,
			"y1": 670,
			"x2": 104,
			"y2": 383,
			"x3": 463,
			"y3": 393,
			"x4": 455,
			"y4": 680
		}
	]
}